donglify/__init__.py
donglify/boot.py
donglify/config.py
donglify/donglify.py
donglify/grub.py
donglify/isos.py
donglify/lib.py
donglify/partition.py
donglify/assets/sd-sulogin.initramfs.hook
donglify/assets/shadow.initramfs
donglify/assets/unicode.pf2
donglify/assets/grub.d/header.cfg
donglify/assets/grub.d/system.cfg
donglify/assets/grub.d/isos/loopback.cfg
donglify/assets/templates/defaultgrub
donglify/assets/templates/mkinitcpio.conf
donglify-20250103.dist-info/METADATA
donglify-20250103.dist-info/WHEEL
donglify-20250103.dist-info/entry_points.txt
donglify-20250103.dist-info/licenses/LICENSE
donglify-20250103.dist-info/RECORD
