Metadata-Version: 2.4
Name: donglify
Version: 20250103
Summary: The ultimate Archlinux encryption USB dongiled setup.
Project-URL: Homepage, https://github.com/ayham-1/donglify
Author-email: ayham-1 <me@ayham.xyz>
Maintainer-email: ayham-1 <me@ayham.xyz>
License: MIT License
License-File: LICENSE
Keywords: archlinux,donglify,encryption,linux,luks,security,usb
Requires-Python: >=3.8
Requires-Dist: prompt-toolkit
Requires-Dist: pydantic
Requires-Dist: termcolor
